MANIFEST.in
README.rst
setup.cfg
setup.py
django_synctool.egg-info/PKG-INFO
django_synctool.egg-info/SOURCES.txt
django_synctool.egg-info/dependency_links.txt
django_synctool.egg-info/not-zip-safe
django_synctool.egg-info/requires.txt
django_synctool.egg-info/top_level.txt
synctool/__init__.py
synctool/auth.py
synctool/client.py
synctool/functions.py
synctool/img.gif
synctool/models.py
synctool/routing.py
synctool/tests.py