Metadata-Version: 1.1
Name: django-synctool
Version: 1.1.0
Summary: Sync data between databases.
Home-page: https://github.com/prestontimmons/django-synctool
Author: Preston Timmons
Author-email: prestontimmons@gmail.com
License: UNKNOWN
Platform: UNKNOWN
Classifier: Framework :: Django
Classifier: License :: OSI Approved :: MIT License
Classifier: Programming Language :: Python
Classifier: Programming Language :: Python :: 2.7
Classifier: Programming Language :: Python :: 3.3
Classifier: Programming Language :: Python :: 3.4
